Metadata-Version: 2.1
Name: quicktools
Version: 0.15
Summary: This is a python functions tools module for enhancing python grammar structures and functions
Home-page: https://github.com/Rainbow-Dreamer/quicktools
Author: Rainbow-Dreamer
Author-email: 1036889495@qq.com
License: AGPLv3
Download-URL: https://github.com/Rainbow-Dreamer/quicktools/archive/0.15.tar.gz
Keywords: tools,mathematics,statistics
Platform: UNKNOWN
Classifier: Development Status :: 3 - Alpha
Classifier: Intended Audience :: Developers
Classifier: Topic :: Software Development :: Build Tools
Classifier: License :: OSI Approved :: GNU Affero General Public License v3
Classifier: Programming Language :: Python :: 3.6
Classifier: Programming Language :: Python :: 3.7
Classifier: Programming Language :: Python :: 3.8
Classifier: Programming Language :: Python :: 3.9
Classifier: Programming Language :: Python :: 3.10
